feltlabs/__init__.py
feltlabs/__main__.py
feltlabs/config.py
feltlabs/model.py
feltlabs/typing.py
feltlabs/algorithm/__init__.py
feltlabs/algorithm/aggregate.py
feltlabs/algorithm/train.py
feltlabs/core/__init__.py
feltlabs/core/cryptography.py
feltlabs/core/data.py
feltlabs/core/json_handler.py
feltlabs/core/ocean.py
feltlabs/core/prompts.py
feltlabs/core/randomness.py
feltlabs/core/storage.py
feltlabs/core/models/__init__.py
feltlabs/core/models/analytics_model.py
feltlabs/core/models/base_model.py
feltlabs/core/models/sklearn_model.py
feltlabs/core/models/tensorflow_model.py
feltlabs/core/models/tensorflow/__init__.py
feltlabs/core/models/tensorflow/cnn_network.py
tests/__init__.py
tests/test_aggregation_analytics.py
tests/test_aggregation_sklearn.py
tests/test_cryptography.py
tests/test_data_load.py
tests/test_import_export.py
tests/test_json_with_numpy.py
tests/test_multi_analytics.py
tests/test_solo_training.py
tests/test_training.py
feltlabs-0.5.2.dist-info/LICENSE
feltlabs-0.5.2.dist-info/METADATA
feltlabs-0.5.2.dist-info/WHEEL
feltlabs-0.5.2.dist-info/entry_points.txt
feltlabs-0.5.2.dist-info/top_level.txt
feltlabs-0.5.2.dist-info/RECORD
